{
  "status": {
    "code": 10000,
    "description": "Ok",
    "req_id": "078395bce23b40be984541e3d382c7fb"
  },
  "outputs": [
    {
      "id": "64f6c1a928b447ee9e580f1ab8c60f83",
      "status": {
        "code": 10000,
        "description": "Ok"
      },
      "created_at": "2019-07-22T08:53:04.523896852Z",
      "model": {
        "id": "HvA_period",
        "name": "HvA_period",
        "created_at": "2019-07-18T13:37:04.079286Z",
        "app_id": "7b53bd99f43149dc81f8a40964ca928a",
        "output_info": {
          "output_config": {
            "concepts_mutually_exclusive": true,
            "closed_environment": true,
            "max_concepts": 0,
            "min_value": 0,
            "test_split_percent": 10
          },
          "message": "Show output_info with: GET /models/{model_id}/output_info",
          "type": "concept",
          "type_ext": "concept"
        },
        "model_version": {
          "id": "e1081a8d9a564c84a655896f3761a306",
          "created_at": "2019-07-19T08:27:37.937596Z",
          "status": {
            "code": 21100,
            "description": "Model trained successfully"
          },
          "total_input_count": 302
        }
      },
      "input": {
        "id": "77394eea443b45c894df4ea7a9002a13",
        "data": {
          "image": {
            "url": "http://ec2-18-191-252-182.us-east-2.compute.amazonaws.com:8182/iiif/2/FO-60-01529/full/922,/0/default.jpg"
          }
        }
      },
      "data": {
        "concepts": [
          {
            "id": "60s",
            "name": "60s",
            "value": 0.7159316,
            "app_id": "7b53bd99f43149dc81f8a40964ca928a"
          },
          {
            "id": "50s",
            "name": "50s",
            "value": 0.10887476,
            "app_id": "7b53bd99f43149dc81f8a40964ca928a"
          },
          {
            "id": "70s",
            "name": "70s",
            "value": 0.072163425,
            "app_id": "7b53bd99f43149dc81f8a40964ca928a"
          },
          {
            "id": "40s",
            "name": "40s",
            "value": 0.065078,
            "app_id": "7b53bd99f43149dc81f8a40964ca928a"
          },
          {
            "id": "20s",
            "name": "20s",
            "value": 0.022280857,
            "app_id": "7b53bd99f43149dc81f8a40964ca928a"
          },
          {
            "id": "30s",
            "name": "30s",
            "value": 0.012032685,
            "app_id": "7b53bd99f43149dc81f8a40964ca928a"
          },
          {
            "id": "10s",
            "name": "10s",
            "value": 0.0018481787,
            "app_id": "7b53bd99f43149dc81f8a40964ca928a"
          },
          {
            "id": "00s",
            "name": "00s",
            "value": 0.0017066236,
            "app_id": "7b53bd99f43149dc81f8a40964ca928a"
          },
          {
            "id": "90s",
            "name": "90s",
            "value": 4.5569916e-05,
            "app_id": "7b53bd99f43149dc81f8a40964ca928a"
          },
          {
            "id": "80s",
            "name": "80s",
            "value": 3.8199218e-05,
            "app_id": "7b53bd99f43149dc81f8a40964ca928a"
          }
        ]
      }
    }
  ]
}
