{
  "responses": [
    {
      "labelAnnotations": [
        {
          "mid": "/m/09g5pq",
          "description": "People",
          "score": 0.9568492,
          "topicality": 0.9568492
        },
        {
          "mid": "/m/068jd",
          "description": "Photograph",
          "score": 0.9480249,
          "topicality": 0.9480249
        },
        {
          "mid": "/m/081pkj",
          "description": "Event",
          "score": 0.78931576,
          "topicality": 0.78931576
        },
        {
          "mid": "/m/019p5q",
          "description": "Gentleman",
          "score": 0.7274816,
          "topicality": 0.7274816
        },
        {
          "mid": "/m/01g6gs",
          "description": "Black-and-white",
          "score": 0.6834213,
          "topicality": 0.6834213
        },
        {
          "mid": "/m/09dhj",
          "description": "Family",
          "score": 0.657708,
          "topicality": 0.657708
        },
        {
          "mid": "/m/03g3w",
          "description": "History",
          "score": 0.62617904,
          "topicality": 0.62617904
        },
        {
          "mid": "/m/01xyhv",
          "description": "Suit",
          "score": 0.56812674,
          "topicality": 0.56812674
        },
        {
          "mid": "/m/08v4gh",
          "description": "Vintage clothing",
          "score": 0.5589101,
          "topicality": 0.5589101
        },
        {
          "mid": "/m/01mwkf",
          "description": "Monochrome",
          "score": 0.5442906,
          "topicality": 0.5442906
        }
      ]
    }
  ]
}
