{
  "responses": [
    {
      "labelAnnotations": [
        {
          "mid": "/m/068jd",
          "description": "Photograph",
          "score": 0.9760221,
          "topicality": 0.9760221
        },
        {
          "mid": "/m/06pg22",
          "description": "Snapshot",
          "score": 0.8797817,
          "topicality": 0.8797817
        },
        {
          "mid": "/m/01g6gs",
          "description": "Black-and-white",
          "score": 0.7811979,
          "topicality": 0.7811979
        },
        {
          "mid": "/m/08v4gh",
          "description": "Vintage clothing",
          "score": 0.774055,
          "topicality": 0.774055
        },
        {
          "mid": "/m/019p5q",
          "description": "Gentleman",
          "score": 0.74867886,
          "topicality": 0.74867886
        },
        {
          "mid": "/m/05wkw",
          "description": "Photography",
          "score": 0.6778865,
          "topicality": 0.6778865
        },
        {
          "mid": "/m/036jvk",
          "description": "Stock photography",
          "score": 0.67624575,
          "topicality": 0.67624575
        },
        {
          "mid": "/m/081hv",
          "description": "Wedding",
          "score": 0.57959265,
          "topicality": 0.57959265
        },
        {
          "mid": "/m/01mwkf",
          "description": "Monochrome",
          "score": 0.5442906,
          "topicality": 0.5442906
        },
        {
          "mid": "/m/016c4t",
          "description": "Ceremony",
          "score": 0.53959894,
          "topicality": 0.53959894
        }
      ]
    }
  ]
}
