{
  "priref": "470005919",
  "Acquisition_source": {
    "acquisition.source.type": {
      "value": "",
      "option": ""
    },
    "acquisition.source.lref": "470014850",
    "acquisition.source": {
      "linkreffield": "acquisition.source.lref",
      "linkfield": "name",
      "linkdb": "G:\\Adlib\\Het Huis van Alijn\\data+people>people",
      "name": "De Bruyne, Christophe",
      "linkref": "470014850"
    }
  },
  "id_number": "47",
  "collection.lref": "470007114",
  "Edit": [
    {
      "edit.date": "2019-03-14",
      "edit.time": "17:21:39",
      "edit.notes": {},
      "edit.name": "eryckx",
      "edit.source": "COLLECT>intern"
    },
    {
      "edit.source": "COLLECT>intern",
      "edit.name": "eryckx",
      "edit.notes": {},
      "edit.date": "2019-02-27",
      "edit.time": "12:27:26"
    },
    {
      "edit.date": "2019-02-20",
      "edit.time": "13:22:08",
      "edit.name": "gvanderhaegen",
      "edit.notes": {},
      "edit.source": "COLLECT>intern"
    },
    {
      "edit.source": "COLLECT>intern",
      "edit.name": "gvanderhaegen",
      "edit.notes": {},
      "edit.time": "18:33:17",
      "edit.date": "2015-10-12"
    },
    {
      "edit.name": "gvanderhaegen",
      "edit.notes": {},
      "edit.date": "2015-10-12",
      "edit.time": "18:25:26",
      "edit.source": "COLLECT>intern"
    },
    {
      "edit.time": "18:17:45",
      "edit.date": "2015-10-12",
      "edit.notes": {},
      "edit.name": "gvanderhaegen",
      "edit.source": "COLLECT>intern"
    },
    {
      "edit.time": "11:53:18",
      "edit.date": "2015-01-20",
      "edit.notes": {},
      "edit.name": "gvanderhaegen",
      "edit.source": "COLLECT>intern"
    },
    {
      "edit.source": "collect>intern",
      "edit.date": "2012-03-28",
      "edit.time": "09:52:54",
      "edit.notes": {},
      "edit.name": "hvaseloy"
    },
    {
      "edit.source": "collect>intern",
      "edit.time": "09:42:45",
      "edit.date": "2012-03-28",
      "edit.notes": {},
      "edit.name": "hvaseloy"
    },
    {
      "edit.time": "09:37:46",
      "edit.date": "2012-03-28",
      "edit.notes": {},
      "edit.name": "hvaseloy",
      "edit.source": "collect>intern"
    },
    {
      "edit.source": "collect>intern",
      "edit.date": "2012-03-28",
      "edit.time": "09:34:51",
      "edit.notes": {},
      "edit.name": "hvaseloy"
    },
    {
      "edit.source": "collect>intern",
      "edit.name": "hvaseloy",
      "edit.notes": {},
      "edit.time": "09:34:14",
      "edit.date": "2012-03-28"
    },
    {
      "edit.name": "hvaseloy",
      "edit.notes": {},
      "edit.time": "09:33:48",
      "edit.date": "2012-03-28",
      "edit.source": "collect>intern"
    }
  ],
  "institution.place": {},
  "institution.name": {
    "name": "Het Huis van Alijn (Gent)",
    "address.place": {},
    "linkdb": "G:\\Adlib\\Het Huis van Alijn\\data+people>people",
    "institution_code": "INST-570",
    "linkref": "470000180",
    "linkfield": "name",
    "linkreffield": "institution.name.lref"
  },
  "object_number": "FO-50-01622",
  "institution.code": "INST-570",
  "input.date": "2012-02-27",
  "collection": {
    "linkdb": "G:\\Adlib\\Het Huis van Alijn\\data+thesau>thesau",
    "linkref": "470007114",
    "term": "digitaal archief/fotoalbum",
    "linkreffield": "collection.lref",
    "linkfield": "term"
  },
  "input.name": "hvalport",
  "check_record": "x",
  "Associated_period": {
    "association.period": {
      "linkref": "470006819",
      "linkdb": "G:\\Adlib\\Het Huis van Alijn\\data+thesau>thesau",
      "linkfield": "term",
      "linkreffield": "association.period.lref",
      "term": "jaren 1950"
    },
    "association.period.note": {},
    "association.period.assoc": {
      "linkreffield": "association.period.assoc.lref",
      "linkfield": "term",
      "linkdb": "G:\\Adlib\\Het Huis van Alijn\\data+thesau>thesau",
      "linkref": "0"
    },
    "association.period.date.start": {},
    "association.period.date.end": {},
    "association.period.assoc.lref": {},
    "association.period.lref": "470006819"
  },
  "Reproduction": {
    "reproduction.format": {},
    "reproduction.type": {},
    "reproduction.creator": {},
    "reproduction.webpublication": {
      "option": "ERFGOED",
      "value": "ERFGOED",
      "text": [
        {
          "language": "0",
          "content": "Heritage"
        },
        {
          "language": "1",
          "content": "Erfgoedinzicht"
        }
      ]
    },
    "reproduction.reference.lref": "470057424",
    "reproduction.reference": {
      "reproduction_type": {},
      "linkreffield": "reproduction.reference.lref",
      "linkfield": "reference_number",
      "creator": {},
      "linkdb": "G:\\Adlib\\Het Huis van Alijn\\data+photo>photo",
      "webpublication": {
        "text": [
          {
            "language": "0",
            "content": "Heritage"
          },
          {
            "language": "1",
            "content": "Erfgoedinzicht"
          }
        ],
        "value": "ERFGOED",
        "option": "ERFGOED"
      },
      "reference_number": "4ab8a566-8b98-6355-8121-fced6e601cad",
      "linkref": "470057424",
      "format": {},
      "production_date": {}
    },
    "reproduction.date": {}
  },
  "acquisition.date": "2012",
  "institution.name.lref": "470000180",
  "input.source": "collect>intern",
  "barcode": "O0458230",
  "Content_subject": [
    {
      "content.subject.name.lref": {},
      "content.subject.position": {},
      "content.subject.lref": "470008831",
      "content.subject.name": {
        "linkdb": "G:\\Adlib\\Het Huis van Alijn\\data+thesau>thesau",
        "linkref": "0",
        "linkfield": "term",
        "linkreffield": "content.subject.name.lref"
      },
      "content.subject.note": {},
      "content.subject": {
        "linkdb": "G:\\Adlib\\Het Huis van Alijn\\data+thesau>thesau",
        "linkref": "470008831",
        "term": "bruidspaar",
        "linkfield": "term",
        "linkreffield": "content.subject.lref"
      },
      "content.subject.tax.lref": {},
      "content.subject.tax": {
        "linkref": "0",
        "linkdb": "G:\\Adlib\\Het Huis van Alijn\\data+taxonom>taxonom",
        "linkreffield": "content.subject.tax.lref",
        "linkfield": "scientific_name"
      },
      "content.subject.identifier": {},
      "content.subject.tax.rank": {
        "option": "",
        "value": ""
      }
    },
    {
      "content.subject.identifier": {},
      "content.subject.tax.rank": {
        "value": "",
        "option": ""
      },
      "content.subject.tax.lref": {},
      "content.subject": {
        "linkdb": "G:\\Adlib\\Het Huis van Alijn\\data+thesau>thesau",
        "linkref": "470001884",
        "term": "priester",
        "linkfield": "term",
        "linkreffield": "content.subject.lref"
      },
      "content.subject.note": {},
      "content.subject.tax": {
        "linkref": "0",
        "linkdb": "G:\\Adlib\\Het Huis van Alijn\\data+taxonom>taxonom",
        "linkfield": "scientific_name",
        "linkreffield": "content.subject.tax.lref"
      },
      "content.subject.position": {},
      "content.subject.name.lref": {},
      "content.subject.name": {
        "linkreffield": "content.subject.name.lref",
        "linkfield": "term",
        "linkref": "0",
        "linkdb": "G:\\Adlib\\Het Huis van Alijn\\data+thesau>thesau"
      },
      "content.subject.lref": "470001884"
    }
  ],
  "distinguishing_features": "DIGITALE COLLECTIE",
  "Associated_subject": [
    {
      "association.subject": {
        "linkdb": "G:\\Adlib\\Het Huis van Alijn\\data+thesau>thesau",
        "linkref": "470002133",
        "term": "huwelijk",
        "linkreffield": "association.subject.lref",
        "linkfield": "term"
      },
      "association.subject.association.lref": {},
      "association.subject.name.lref": {},
      "association.subject.tax": {
        "linkref": "0",
        "linkdb": "G:\\Adlib\\Het Huis van Alijn\\data+taxonom>taxonom",
        "linkfield": "scientific_name",
        "linkreffield": "association.subject.tax.lref"
      },
      "association.subject.tax.rank": {
        "value": "",
        "option": ""
      },
      "association.subject.type": {
        "value": "",
        "option": ""
      },
      "association.subject.note": {},
      "association.subject.date.end": {},
      "association.subject.date.start": {},
      "association.subject.name": {
        "linkref": "0",
        "linkdb": "G:\\Adlib\\Het Huis van Alijn\\data+thesau>thesau",
        "linkreffield": "association.subject.name.lref",
        "linkfield": "term"
      },
      "association.subject.tax.lref": {},
      "association.subject.association": {
        "linkref": "0",
        "linkdb": "G:\\Adlib\\Het Huis van Alijn\\data+thesau>thesau",
        "linkfield": "term",
        "linkreffield": "association.subject.association.lref"
      },
      "association.subject.lref": "470002133"
    },
    {
      "association.subject.lref": "470002018",
      "association.subject.association": {
        "linkdb": "G:\\Adlib\\Het Huis van Alijn\\data+thesau>thesau",
        "linkref": "0",
        "linkreffield": "association.subject.association.lref",
        "linkfield": "term"
      },
      "association.subject.tax.lref": {},
      "association.subject.name": {
        "linkfield": "term",
        "linkreffield": "association.subject.name.lref",
        "linkdb": "G:\\Adlib\\Het Huis van Alijn\\data+thesau>thesau",
        "linkref": "0"
      },
      "association.subject.date.start": {},
      "association.subject.type": {
        "option": "",
        "value": ""
      },
      "association.subject.date.end": {},
      "association.subject.note": {},
      "association.subject.tax.rank": {
        "value": "",
        "option": ""
      },
      "association.subject.tax": {
        "linkdb": "G:\\Adlib\\Het Huis van Alijn\\data+taxonom>taxonom",
        "linkref": "0",
        "linkfield": "scientific_name",
        "linkreffield": "association.subject.tax.lref"
      },
      "association.subject.association.lref": {},
      "association.subject": {
        "linkref": "470002018",
        "linkdb": "G:\\Adlib\\Het Huis van Alijn\\data+thesau>thesau",
        "linkfield": "term",
        "linkreffield": "association.subject.lref",
        "term": "kerk"
      },
      "association.subject.name.lref": {}
    },
    {
      "association.subject.tax.rank": {
        "option": "",
        "value": ""
      },
      "association.subject.type": {
        "value": "",
        "option": ""
      },
      "association.subject.date.end": {},
      "association.subject.note": {},
      "association.subject": {
        "term": "Aalst",
        "linkreffield": "association.subject.lref",
        "linkfield": "term",
        "linkdb": "G:\\Adlib\\Het Huis van Alijn\\data+thesau>thesau",
        "linkref": "470000935"
      },
      "association.subject.association.lref": {},
      "association.subject.tax": {
        "linkdb": "G:\\Adlib\\Het Huis van Alijn\\data+taxonom>taxonom",
        "linkref": "0",
        "linkreffield": "association.subject.tax.lref",
        "linkfield": "scientific_name"
      },
      "association.subject.name.lref": {},
      "association.subject.tax.lref": {},
      "association.subject.lref": "470000935",
      "association.subject.association": {
        "linkreffield": "association.subject.association.lref",
        "linkfield": "term",
        "linkref": "0",
        "linkdb": "G:\\Adlib\\Het Huis van Alijn\\data+thesau>thesau"
      },
      "association.subject.date.start": {},
      "association.subject.name": {
        "linkdb": "G:\\Adlib\\Het Huis van Alijn\\data+thesau>thesau",
        "linkref": "0",
        "linkfield": "term",
        "linkreffield": "association.subject.name.lref"
      }
    }
  ],
  "Object_name": {
    "object_name.type": {
      "linkreffield": "object_name.type.lref",
      "linkfield": "term",
      "term": "foto",
      "linkref": "470001732",
      "linkdb": "G:\\Adlib\\Het Huis van Alijn\\data+thesau>thesau"
    },
    "object_name.authority.lref": {},
    "object_name.notes": {},
    "object_name": {
      "linkreffield": "object_name.lref",
      "linkfield": "term",
      "term": "digitale afbeelding",
      "linkref": "470009036",
      "linkdb": "G:\\Adlib\\Het Huis van Alijn\\data+thesau>thesau"
    },
    "object_name.type.lref": "470001732",
    "object_name.lref": "470009036",
    "object_name.authority": {
      "linkreffield": "object_name.authority.lref",
      "linkfield": "term",
      "linkref": "0",
      "linkdb": "G:\\Adlib\\Het Huis van Alijn\\data+thesau>thesau"
    }
  },
  "ACCESS_RIGHTS": [
    {
      "record_access.rights": {
        "option": "1",
        "value": "1",
        "text": [
          {
            "language": "0",
            "content": "Read"
          },
          {
            "content": "Lezen",
            "language": "1"
          },
          {
            "content": "Lire",
            "language": "2"
          }
        ]
      },
      "record_access.user": "guest"
    },
    {
      "record_access.user": "MOVEcgen",
      "record_access.rights": {
        "option": "2",
        "text": [
          {
            "content": "Read and Write",
            "language": "0"
          },
          {
            "content": "Lezen en schrijven",
            "language": "1"
          },
          {
            "content": "Lire et écrire",
            "language": "2"
          }
        ],
        "value": "2"
      }
    },
    {
      "record_access.user": "PWVIIS",
      "record_access.rights": {
        "text": [
          {
            "language": "0",
            "content": "Read"
          },
          {
            "language": "1",
            "content": "Lezen"
          },
          {
            "content": "Lire",
            "language": "2"
          }
        ],
        "value": "1",
        "option": "1"
      }
    }
  ],
  "input.time": "15:46:41",
  "Description": {
    "description": "De viering vond plaats in de Sint-Jozefkerk van Aalst.",
    "description.date": {},
    "description.name": {}
  },
  "Title": {
    "title.type": {},
    "title": "Huwelijksmis Angèle en Jean, Aalst, 1958",
    "title.notes": {}
  },
  "administration_name": "WEB_RITUEEL_HUWELIJK_FOTO",
  "record_type": {
    "text": [
      {
        "content": "single object",
        "language": "0"
      },
      {
        "content": "enkelvoudig object",
        "language": "1"
      },
      {
        "content": "objet individuel",
        "language": "2"
      },
      {
        "language": "3",
        "content": "Einzelnes Objekt"
      },
      {
        "language": "5",
        "content": "oggetto singolo"
      }
    ],
    "value": "enkelvoudig object",
    "option": "OBJECT"
  },
  "Production_date": {
    "production.date.start.prec": {},
    "production.date.end.prec": {},
    "production.date.start": "1958-02-01",
    "production.date.end": {}
  },
  "record_access.owner": "MOVEhva"
}
