{
  "status": {
    "code": 10000,
    "description": "Ok",
    "req_id": "2a92e0528a454ff2b555a9054f37e082"
  },
  "outputs": [
    {
      "id": "f6e1c66bbb6848819171daad12073765",
      "status": {
        "code": 10000,
        "description": "Ok"
      },
      "created_at": "2019-04-01T16:05:17.950338607Z",
      "model": {
        "id": "aaa03c23b3724a16a56b629203edc62c",
        "name": "general",
        "created_at": "2016-03-09T17:11:39.608845Z",
        "app_id": "main",
        "output_info": {
          "message": "Show output_info with: GET /models/{model_id}/output_info",
          "type": "concept",
          "type_ext": "concept"
        },
        "model_version": {
          "id": "aa7f35c01e0642fda5cf400f543e7c40",
          "created_at": "2018-03-06T21:10:24.454834Z",
          "status": {
            "code": 21100,
            "description": "Model trained successfully"
          }
        },
        "display_name": "General"
      },
      "input": {
        "id": "a752358c1208432388d1fa0183c272e7",
        "data": {
          "image": {
            "url": "http://ec2-18-191-252-182.us-east-2.compute.amazonaws.com:8182/iiif/2/FO-40-00787/full/full/0/default.jpg"
          }
        }
      },
      "data": {
        "concepts": [
          {
            "id": "ai_l8TKp2h5",
            "name": "people",
            "value": 0.9989404,
            "app_id": "main"
          },
          {
            "id": "ai_86sS08Pw",
            "name": "wear",
            "value": 0.9906391,
            "app_id": "main"
          },
          {
            "id": "ai_TJ9wFfK5",
            "name": "portrait",
            "value": 0.98323625,
            "app_id": "main"
          },
          {
            "id": "ai_SVshtN54",
            "name": "one",
            "value": 0.979112,
            "app_id": "main"
          },
          {
            "id": "ai_VPmHr5bm",
            "name": "adult",
            "value": 0.9617036,
            "app_id": "main"
          },
          {
            "id": "ai_94cQBGlt",
            "name": "two",
            "value": 0.95118284,
            "app_id": "main"
          },
          {
            "id": "ai_qcLd7fgc",
            "name": "child",
            "value": 0.9461655,
            "app_id": "main"
          },
          {
            "id": "ai_qX2mzVVX",
            "name": "outerwear",
            "value": 0.9445149,
            "app_id": "main"
          },
          {
            "id": "ai_p4QNNm1l",
            "name": "administration",
            "value": 0.9365093,
            "app_id": "main"
          },
          {
            "id": "ai_ntt6Zlfl",
            "name": "outfit",
            "value": 0.9250282,
            "app_id": "main"
          },
          {
            "id": "ai_L83krFdq",
            "name": "veil",
            "value": 0.92316943,
            "app_id": "main"
          },
          {
            "id": "ai_snJqkVxZ",
            "name": "coat",
            "value": 0.905491,
            "app_id": "main"
          },
          {
            "id": "ai_vNPf6vm0",
            "name": "princess",
            "value": 0.8935877,
            "app_id": "main"
          },
          {
            "id": "ai_gJm9b4ts",
            "name": "vintage",
            "value": 0.87847364,
            "app_id": "main"
          },
          {
            "id": "ai_nNRnTLMl",
            "name": "leader",
            "value": 0.87622213,
            "app_id": "main"
          },
          {
            "id": "ai_RQccV41p",
            "name": "woman",
            "value": 0.87337947,
            "app_id": "main"
          },
          {
            "id": "ai_1p2zMmqb",
            "name": "retro",
            "value": 0.8613779,
            "app_id": "main"
          },
          {
            "id": "ai_JBPqff8z",
            "name": "art",
            "value": 0.86018074,
            "app_id": "main"
          },
          {
            "id": "ai_MMxKGmfT",
            "name": "actress",
            "value": 0.85412365,
            "app_id": "main"
          },
          {
            "id": "ai_dPSZc2sM",
            "name": "lid",
            "value": 0.8340195,
            "app_id": "main"
          }
        ]
      }
    }
  ]
}
