{
  "status": {
    "code": 10000,
    "description": "Ok",
    "req_id": "ed8c8eb4ed864cc5903baf119d923f62"
  },
  "outputs": [
    {
      "id": "14f4c5e3446449d492625fe6705de7dd",
      "status": {
        "code": 10000,
        "description": "Ok"
      },
      "created_at": "2019-03-31T21:46:54.190471714Z",
      "model": {
        "id": "eee28c313d69466f836ab83287a54ed9",
        "name": "travel-v1.0",
        "created_at": "2016-09-17T22:18:59.955626Z",
        "app_id": "main",
        "output_info": {
          "message": "Show output_info with: GET /models/{model_id}/output_info",
          "type": "concept",
          "type_ext": "concept"
        },
        "model_version": {
          "id": "d2ffbf9730fd41fea79063270847be82",
          "created_at": "2016-09-17T22:18:59.955626Z",
          "status": {
            "code": 21100,
            "description": "Model trained successfully"
          }
        },
        "display_name": "Travel"
      },
      "input": {
        "id": "51c56a032e2c4fddbff8f9ad7cd30e34",
        "data": {
          "image": {
            "url": "http://ec2-18-191-252-182.us-east-2.compute.amazonaws.com:8182/iiif/2/FO-60-00751/full/full/0/default.jpg"
          }
        }
      },
      "data": {
        "concepts": [
          {
            "id": "ai_2QTpTbBt",
            "name": "People",
            "value": 0.7830231,
            "app_id": "main"
          },
          {
            "id": "ai_zF1MvGHt",
            "name": "Television",
            "value": 0.5298238,
            "app_id": "main"
          },
          {
            "id": "ai_v5zlpKkc",
            "name": "Tennis Court",
            "value": 0.43832365,
            "app_id": "main"
          },
          {
            "id": "ai_sf6B79BS",
            "name": "Sports & Activities",
            "value": 0.35253966,
            "app_id": "main"
          },
          {
            "id": "ai_hmSzCZd5",
            "name": "Daytime",
            "value": 0.3485303,
            "app_id": "main"
          },
          {
            "id": "ai_4NvhWszJ",
            "name": "Snow & Ski Sports",
            "value": 0.3376057,
            "app_id": "main"
          },
          {
            "id": "ai_NVNKLrCW",
            "name": "Details",
            "value": 0.28550017,
            "app_id": "main"
          },
          {
            "id": "ai_XB2b9m4v",
            "name": "Summer",
            "value": 0.266174,
            "app_id": "main"
          },
          {
            "id": "ai_6bSB4lrf",
            "name": "Couch",
            "value": 0.26512107,
            "app_id": "main"
          },
          {
            "id": "ai_B1nLlMJ8",
            "name": "Wedding",
            "value": 0.2575734,
            "app_id": "main"
          },
          {
            "id": "ai_8v2Tm2Gl",
            "name": "Hot Tub",
            "value": 0.25610146,
            "app_id": "main"
          },
          {
            "id": "ai_zTxfQQKH",
            "name": "Kids Area",
            "value": 0.24781005,
            "app_id": "main"
          },
          {
            "id": "ai_CVQVtMzc",
            "name": "Nighttime",
            "value": 0.23001055,
            "app_id": "main"
          },
          {
            "id": "ai_7kVDV8Md",
            "name": "Bicycling",
            "value": 0.22724706,
            "app_id": "main"
          },
          {
            "id": "ai_2jkxl4Fz",
            "name": "Spring",
            "value": 0.21949029,
            "app_id": "main"
          },
          {
            "id": "ai_MbpTFJxj",
            "name": "Garden",
            "value": 0.20317988,
            "app_id": "main"
          },
          {
            "id": "ai_rRbfXwwx",
            "name": "Chair",
            "value": 0.19806685,
            "app_id": "main"
          },
          {
            "id": "ai_J2x9qKdS",
            "name": "Animals",
            "value": 0.1907018,
            "app_id": "main"
          },
          {
            "id": "ai_qDnbBFvp",
            "name": "Balcony",
            "value": 0.18209669,
            "app_id": "main"
          },
          {
            "id": "ai_PtsQBLC8",
            "name": "Fireplace",
            "value": 0.1743118,
            "app_id": "main"
          }
        ]
      }
    }
  ]
}
