{
  "status": {
    "code": 10000,
    "description": "Ok",
    "req_id": "10c13aef5a3e4f57a55153b3d784090e"
  },
  "outputs": [
    {
      "id": "01a4d2ac66ba42189ec6a70a80f6069e",
      "status": {
        "code": 10000,
        "description": "Ok"
      },
      "created_at": "2019-04-01T16:12:23.543903236Z",
      "model": {
        "id": "aaa03c23b3724a16a56b629203edc62c",
        "name": "general",
        "created_at": "2016-03-09T17:11:39.608845Z",
        "app_id": "main",
        "output_info": {
          "message": "Show output_info with: GET /models/{model_id}/output_info",
          "type": "concept",
          "type_ext": "concept"
        },
        "model_version": {
          "id": "aa7f35c01e0642fda5cf400f543e7c40",
          "created_at": "2018-03-06T21:10:24.454834Z",
          "status": {
            "code": 21100,
            "description": "Model trained successfully"
          }
        },
        "display_name": "General"
      },
      "input": {
        "id": "4330422f80d843bf9b69c0566af7d94f",
        "data": {
          "image": {
            "url": "http://ec2-18-191-252-182.us-east-2.compute.amazonaws.com:8182/iiif/2/DIA-0049-0411/full/full/0/default.jpg"
          }
        }
      },
      "data": {
        "concepts": [
          {
            "id": "ai_l8TKp2h5",
            "name": "people",
            "value": 0.99643195,
            "app_id": "main"
          },
          {
            "id": "ai_bmls4LpL",
            "name": "group",
            "value": 0.99466187,
            "app_id": "main"
          },
          {
            "id": "ai_MljhkW17",
            "name": "many",
            "value": 0.9918331,
            "app_id": "main"
          },
          {
            "id": "ai_GjVpxXrs",
            "name": "street",
            "value": 0.97488505,
            "app_id": "main"
          },
          {
            "id": "ai_WBQfVV0p",
            "name": "city",
            "value": 0.9693238,
            "app_id": "main"
          },
          {
            "id": "ai_VRmbGVWh",
            "name": "travel",
            "value": 0.9602174,
            "app_id": "main"
          },
          {
            "id": "ai_sd6DKdXp",
            "name": "group together",
            "value": 0.9561396,
            "app_id": "main"
          },
          {
            "id": "ai_dxSG2s86",
            "name": "man",
            "value": 0.954989,
            "app_id": "main"
          },
          {
            "id": "ai_13NdwKqz",
            "name": "festival",
            "value": 0.92888296,
            "app_id": "main"
          },
          {
            "id": "ai_RQccV41p",
            "name": "woman",
            "value": 0.92501056,
            "app_id": "main"
          },
          {
            "id": "ai_2w0dzpC8",
            "name": "tourist",
            "value": 0.9218518,
            "app_id": "main"
          },
          {
            "id": "ai_86sS08Pw",
            "name": "wear",
            "value": 0.9104254,
            "app_id": "main"
          },
          {
            "id": "ai_Zmhsv0Ch",
            "name": "outdoors",
            "value": 0.9040364,
            "app_id": "main"
          },
          {
            "id": "ai_VPmHr5bm",
            "name": "adult",
            "value": 0.9019396,
            "app_id": "main"
          },
          {
            "id": "ai_qcLd7fgc",
            "name": "child",
            "value": 0.8982433,
            "app_id": "main"
          },
          {
            "id": "ai_FWCjC8jZ",
            "name": "architecture",
            "value": 0.8902377,
            "app_id": "main"
          },
          {
            "id": "ai_dJ15S9s6",
            "name": "crowd",
            "value": 0.883843,
            "app_id": "main"
          },
          {
            "id": "ai_nfd9DXhN",
            "name": "tourism",
            "value": 0.83371335,
            "app_id": "main"
          },
          {
            "id": "ai_358VqvJT",
            "name": "religion",
            "value": 0.8249082,
            "app_id": "main"
          },
          {
            "id": "ai_CpFBRWzD",
            "name": "urban",
            "value": 0.81795084,
            "app_id": "main"
          }
        ]
      }
    }
  ]
}
