{
  "status": {
    "code": 10000,
    "description": "Ok",
    "req_id": "f9685467e2824dabb6c1bcc9c64f8889"
  },
  "outputs": [
    {
      "id": "a0a043328c2641c181dd810d2ff4155d",
      "status": {
        "code": 10000,
        "description": "Ok"
      },
      "created_at": "2019-04-01T15:50:30.532333689Z",
      "model": {
        "id": "aaa03c23b3724a16a56b629203edc62c",
        "name": "general",
        "created_at": "2016-03-09T17:11:39.608845Z",
        "app_id": "main",
        "output_info": {
          "message": "Show output_info with: GET /models/{model_id}/output_info",
          "type": "concept",
          "type_ext": "concept"
        },
        "model_version": {
          "id": "aa7f35c01e0642fda5cf400f543e7c40",
          "created_at": "2018-03-06T21:10:24.454834Z",
          "status": {
            "code": 21100,
            "description": "Model trained successfully"
          }
        },
        "display_name": "General"
      },
      "input": {
        "id": "b80e0bdcf5794096827d42fcd0658f20",
        "data": {
          "image": {
            "url": "http://ec2-18-191-252-182.us-east-2.compute.amazonaws.com:8182/iiif/2/FO-40-00614/full/full/0/default.jpg"
          }
        }
      },
      "data": {
        "concepts": [
          {
            "id": "ai_l8TKp2h5",
            "name": "people",
            "value": 0.9988392,
            "app_id": "main"
          },
          {
            "id": "ai_TJ9wFfK5",
            "name": "portrait",
            "value": 0.9955391,
            "app_id": "main"
          },
          {
            "id": "ai_qZ0g3FNJ",
            "name": "wedding",
            "value": 0.9886219,
            "app_id": "main"
          },
          {
            "id": "ai_dLXPlbfc",
            "name": "flower arrangement",
            "value": 0.98553526,
            "app_id": "main"
          },
          {
            "id": "ai_jBg5fXBx",
            "name": "groom",
            "value": 0.9773522,
            "app_id": "main"
          },
          {
            "id": "ai_94cQBGlt",
            "name": "two",
            "value": 0.9765955,
            "app_id": "main"
          },
          {
            "id": "ai_VPmHr5bm",
            "name": "adult",
            "value": 0.97387946,
            "app_id": "main"
          },
          {
            "id": "ai_RQccV41p",
            "name": "woman",
            "value": 0.964164,
            "app_id": "main"
          },
          {
            "id": "ai_86sS08Pw",
            "name": "wear",
            "value": 0.94087476,
            "app_id": "main"
          },
          {
            "id": "ai_dxSG2s86",
            "name": "man",
            "value": 0.9402325,
            "app_id": "main"
          },
          {
            "id": "ai_k76BrtPJ",
            "name": "music",
            "value": 0.9283265,
            "app_id": "main"
          },
          {
            "id": "ai_bmls4LpL",
            "name": "group",
            "value": 0.9256585,
            "app_id": "main"
          },
          {
            "id": "ai_swtdphX8",
            "name": "love",
            "value": 0.9215165,
            "app_id": "main"
          },
          {
            "id": "ai_GxSDhQ34",
            "name": "facial expression",
            "value": 0.9211212,
            "app_id": "main"
          },
          {
            "id": "ai_dFJQwFn7",
            "name": "sepia",
            "value": 0.92052037,
            "app_id": "main"
          },
          {
            "id": "ai_MMxKGmfT",
            "name": "actress",
            "value": 0.9178979,
            "app_id": "main"
          },
          {
            "id": "ai_vMZvx6j4",
            "name": "monochrome",
            "value": 0.91757107,
            "app_id": "main"
          },
          {
            "id": "ai_VZJZqn8Q",
            "name": "bride",
            "value": 0.91148895,
            "app_id": "main"
          },
          {
            "id": "ai_ntt6Zlfl",
            "name": "outfit",
            "value": 0.89391524,
            "app_id": "main"
          },
          {
            "id": "ai_p05ZRNJl",
            "name": "interaction",
            "value": 0.89151245,
            "app_id": "main"
          }
        ]
      }
    }
  ]
}
