{"status":{"code":10000,"description":"Ok","req_id":"be8723b3a5ee4c4990d394d13da4e336"},"outputs":[{"id":"27971e869bd14dd9bae55c3fa1f17d0c","status":{"code":10000,"description":"Ok"},"created_at":"2019-03-29T09:55:38.677011624Z","model":{"id":"aaa03c23b3724a16a56b629203edc62c","name":"general","created_at":"2016-03-09T17:11:39.608845Z","app_id":"main","output_info":{"message":"Show output_info with: GET /models/{model_id}/output_info","type":"concept","type_ext":"concept"},"model_version":{"id":"aa9ca48295b37401f8af92ad1af0d91d","created_at":"2016-07-13T01:19:12.147644Z","status":{"code":21100,"description":"Model trained successfully"}},"display_name":"General"},"input":{"id":"1a0fad9c65ab4d588c5e595361c91b45","data":{"image":{"url":"http://ec2-18-191-252-182.us-east-2.compute.amazonaws.com:8182/iiif/2/FO-40-00727/full/full/0/default.jpg"}}},"data":{"concepts":[{"id":"ai_l8TKp2h5","name":"volk","value":0.99934304,"app_id":"main"},{"id":"ai_94cQBGlt","name":"twee","value":0.98331475,"app_id":"main"},{"id":"ai_VPmHr5bm","name":"volwassen","value":0.9807366,"app_id":"main"},{"id":"ai_86sS08Pw","name":"kleding","value":0.97277284,"app_id":"main"},{"id":"ai_p4QNNm1l","name":"administratie","value":0.9649247,"app_id":"main"},{"id":"ai_TJ9wFfK5","name":"portret","value":0.9625269,"app_id":"main"},{"id":"ai_dxSG2s86","name":"mannelijk","value":0.95339906,"app_id":"main"},{"id":"ai_KTVs6s9T","name":"drie","value":0.9304079,"app_id":"main"},{"id":"ai_RQccV41p","name":"vrouw","value":0.9222864,"app_id":"main"},{"id":"ai_nNRnTLMl","name":"leider","value":0.8899456,"app_id":"main"},{"id":"ai_bmls4LpL","name":"groep (abstractie)","value":0.8843322,"app_id":"main"},{"id":"ai_SVshtN54","name":"een","value":0.8377801,"app_id":"main"},{"id":"ai_qcLd7fgc","name":"kind","value":0.82492507,"app_id":"main"},{"id":"ai_0SL2mdXt","name":"militaire tak","value":0.81939197,"app_id":"main"},{"id":"ai_GxSDhQ34","name":"gezichtsuitdrukking","value":0.8180039,"app_id":"main"},{"id":"ai_L3mzGfDT","name":"nageslacht","value":0.8070146,"app_id":"main"},{"id":"ai_Br1sz8D7","name":"oorlog","value":0.80367154,"app_id":"main"},{"id":"ai_sd6DKdXp","name":"groep","value":0.7891966,"app_id":"main"},{"id":"ai_ntt6Zlfl","name":"rig (kleding)","value":0.78849757,"app_id":"main"},{"id":"ai_9GJPfJ2J","name":"broers en zussen","value":0.7840205,"app_id":"main"}]}}]}