{"status":{"code":10000,"description":"Ok","req_id":"a3c55c7726fd424ebe3dafbcf9c3828b"},"outputs":[{"id":"144f8b44efc841148a8644464725348c","status":{"code":10000,"description":"Ok"},"created_at":"2019-03-29T09:49:37.246053913Z","model":{"id":"aaa03c23b3724a16a56b629203edc62c","name":"general","created_at":"2016-03-09T17:11:39.608845Z","app_id":"main","output_info":{"message":"Show output_info with: GET /models/{model_id}/output_info","type":"concept","type_ext":"concept"},"model_version":{"id":"aa9ca48295b37401f8af92ad1af0d91d","created_at":"2016-07-13T01:19:12.147644Z","status":{"code":21100,"description":"Model trained successfully"}},"display_name":"General"},"input":{"id":"a05099a5c3b64c5f90a5851a91ca09a4","data":{"image":{"url":"http://ec2-18-191-252-182.us-east-2.compute.amazonaws.com:8182/iiif/2/FO-60-01503/full/full/0/default.jpg"}}},"data":{"concepts":[{"id":"ai_l8TKp2h5","name":"volk","value":0.9937249,"app_id":"main"},{"id":"ai_bmls4LpL","name":"groep (abstractie)","value":0.98919713,"app_id":"main"},{"id":"ai_s6Fp0k1f","name":"zwanen","value":0.98667073,"app_id":"main"},{"id":"ai_VPmHr5bm","name":"volwassen","value":0.96174777,"app_id":"main"},{"id":"ai_94cQBGlt","name":"twee","value":0.9593024,"app_id":"main"},{"id":"ai_G2PvQtHz","name":"vogels","value":0.9564477,"app_id":"main"},{"id":"ai_XB21BKM9","name":"verscheidene","value":0.9516992,"app_id":"main"},{"id":"ai_SVshtN54","name":"een","value":0.9458888,"app_id":"main"},{"id":"ai_MljhkW17","name":"veel","value":0.93015563,"app_id":"main"},{"id":"ai_BlL0wSQh","name":"waterlichaam","value":0.9073,"app_id":"main"},{"id":"ai_RQccV41p","name":"vrouw","value":0.89753973,"app_id":"main"},{"id":"ai_x3vjxJsW","name":"behuizing","value":0.8795824,"app_id":"main"},{"id":"ai_L83krFdq","name":"hoofddeksel","value":0.87952685,"app_id":"main"},{"id":"ai_3DwNCm6R","name":"meer (watervlakte)","value":0.87843144,"app_id":"main"},{"id":"ai_KTVs6s9T","name":"drie","value":0.8721721,"app_id":"main"},{"id":"ai_sd6DKdXp","name":"groep","value":0.84346616,"app_id":"main"},{"id":"ai_vB28NG85","name":"pluimvee","value":0.8369092,"app_id":"main"},{"id":"ai_PLL23MG4","name":"vier","value":0.8344885,"app_id":"main"},{"id":"ai_RxKbK54N","name":"ganzen","value":0.82846946,"app_id":"main"},{"id":"ai_9qgdgtDK","name":"eenden","value":0.81605214,"app_id":"main"}]}}]}