{"status":{"code":10000,"description":"Ok","req_id":"01d3658507784f27a1311546bb8ee8a6"},"outputs":[{"id":"2c9ce3bc167b4cc1afd30aedb02c09f6","status":{"code":10000,"description":"Ok"},"created_at":"2019-03-29T09:49:25.089642154Z","model":{"id":"aaa03c23b3724a16a56b629203edc62c","name":"general","created_at":"2016-03-09T17:11:39.608845Z","app_id":"main","output_info":{"message":"Show output_info with: GET /models/{model_id}/output_info","type":"concept","type_ext":"concept"},"model_version":{"id":"aa9ca48295b37401f8af92ad1af0d91d","created_at":"2016-07-13T01:19:12.147644Z","status":{"code":21100,"description":"Model trained successfully"}},"display_name":"General"},"input":{"id":"a0161844fb4a4e2d9771c9dd726d71f7","data":{"image":{"url":"http://ec2-18-191-252-182.us-east-2.compute.amazonaws.com:8182/iiif/2/FO-60-01499/full/full/0/default.jpg"}}},"data":{"concepts":[{"id":"ai_l8TKp2h5","name":"volk","value":0.9978164,"app_id":"main"},{"id":"ai_bmls4LpL","name":"groep (abstractie)","value":0.9966965,"app_id":"main"},{"id":"ai_sd6DKdXp","name":"groep","value":0.9913167,"app_id":"main"},{"id":"ai_VPmHr5bm","name":"volwassen","value":0.96938586,"app_id":"main"},{"id":"ai_RQccV41p","name":"vrouw","value":0.95506006,"app_id":"main"},{"id":"ai_qcLd7fgc","name":"kind","value":0.95240664,"app_id":"main"},{"id":"ai_nNRnTLMl","name":"leider","value":0.9515812,"app_id":"main"},{"id":"ai_dxSG2s86","name":"mannelijk","value":0.94920194,"app_id":"main"},{"id":"ai_MljhkW17","name":"veel","value":0.9476002,"app_id":"main"},{"id":"ai_PLL23MG4","name":"vier","value":0.9474665,"app_id":"main"},{"id":"ai_XB21BKM9","name":"verscheidene","value":0.94640833,"app_id":"main"},{"id":"ai_m3kStt2H","name":"vijf","value":0.92286175,"app_id":"main"},{"id":"ai_MMxKGmfT","name":"actrice","value":0.9200847,"app_id":"main"},{"id":"ai_ntt6Zlfl","name":"rig (kleding)","value":0.9191352,"app_id":"main"},{"id":"ai_p4QNNm1l","name":"administratie","value":0.91166294,"app_id":"main"},{"id":"ai_qZ0g3FNJ","name":"huwelijk (ritueel)","value":0.9036431,"app_id":"main"},{"id":"ai_GxSDhQ34","name":"gezichtsuitdrukking","value":0.88271546,"app_id":"main"},{"id":"ai_86sS08Pw","name":"kleding","value":0.880005,"app_id":"main"},{"id":"ai_L83krFdq","name":"hoofddeksel","value":0.8737259,"app_id":"main"},{"id":"ai_FLxBx1Cz","name":"ceremonie","value":0.8637447,"app_id":"main"}]}}]}