{
  "status": {
    "code": 10000,
    "description": "Ok",
    "req_id": "e35f2230c06e4d19a10fca526027f8a5"
  },
  "inputs": [
    {
      "id": "d00f5a3b7a314a5b91f6c5516d23f032",
      "data": {
        "image": {
          "url": "http://ec2-18-191-252-182.us-east-2.compute.amazonaws.com:8182/iiif/2/FO-60-00935/full/922,/0/default.jpg"
        },
        "concepts": [
          {
            "id": "geboorte",
            "name": "geboorte",
            "value": 1,
            "app_id": "1b9b01460b944923a9eb1578668d4ea6"
          }
        ]
      },
      "created_at": "2019-07-13T21:04:01.651791170Z",
      "modified_at": "2019-07-13T21:04:02.995345157Z",
      "status": {
        "code": 30000,
        "description": "Download complete"
      }
    }
  ]
}
