{
  "status": {
    "code": 10000,
    "description": "Ok",
    "req_id": "aaaee16b835643c089de6a7086005617"
  },
  "outputs": [
    {
      "id": "062063043d244131b0ec7e40f4ec0973",
      "status": {
        "code": 10000,
        "description": "Ok"
      },
      "created_at": "2019-04-01T15:46:36.250505596Z",
      "model": {
        "id": "aaa03c23b3724a16a56b629203edc62c",
        "name": "general",
        "created_at": "2016-03-09T17:11:39.608845Z",
        "app_id": "main",
        "output_info": {
          "message": "Show output_info with: GET /models/{model_id}/output_info",
          "type": "concept",
          "type_ext": "concept"
        },
        "model_version": {
          "id": "aa7f35c01e0642fda5cf400f543e7c40",
          "created_at": "2018-03-06T21:10:24.454834Z",
          "status": {
            "code": 21100,
            "description": "Model trained successfully"
          }
        },
        "display_name": "General"
      },
      "input": {
        "id": "b11f53174a5442beaf51a9ec4adfdc8b",
        "data": {
          "image": {
            "url": "http://ec2-18-191-252-182.us-east-2.compute.amazonaws.com:8182/iiif/2/FO-60-00083/full/full/0/default.jpg"
          }
        }
      },
      "data": {
        "concepts": [
          {
            "id": "ai_l8TKp2h5",
            "name": "people",
            "value": 0.99535745,
            "app_id": "main"
          },
          {
            "id": "ai_RQccV41p",
            "name": "woman",
            "value": 0.96842504,
            "app_id": "main"
          },
          {
            "id": "ai_qcLd7fgc",
            "name": "child",
            "value": 0.9526804,
            "app_id": "main"
          },
          {
            "id": "ai_j09mzT6j",
            "name": "family",
            "value": 0.9411004,
            "app_id": "main"
          },
          {
            "id": "ai_VPmHr5bm",
            "name": "adult",
            "value": 0.92517906,
            "app_id": "main"
          },
          {
            "id": "ai_5mgGJnNc",
            "name": "baby",
            "value": 0.8963663,
            "app_id": "main"
          },
          {
            "id": "ai_xQbBc1zb",
            "name": "girl",
            "value": 0.89489776,
            "app_id": "main"
          },
          {
            "id": "ai_bmls4LpL",
            "name": "group",
            "value": 0.87672,
            "app_id": "main"
          },
          {
            "id": "ai_dxSG2s86",
            "name": "man",
            "value": 0.8485261,
            "app_id": "main"
          },
          {
            "id": "ai_94cQBGlt",
            "name": "two",
            "value": 0.8446948,
            "app_id": "main"
          },
          {
            "id": "ai_86sS08Pw",
            "name": "wear",
            "value": 0.8417579,
            "app_id": "main"
          },
          {
            "id": "ai_qZ0g3FNJ",
            "name": "wedding",
            "value": 0.8377597,
            "app_id": "main"
          },
          {
            "id": "ai_6HDtKSP7",
            "name": "event",
            "value": 0.8151444,
            "app_id": "main"
          },
          {
            "id": "ai_swtdphX8",
            "name": "love",
            "value": 0.81394583,
            "app_id": "main"
          },
          {
            "id": "ai_KTVs6s9T",
            "name": "three",
            "value": 0.80691123,
            "app_id": "main"
          },
          {
            "id": "ai_nNRnTLMl",
            "name": "leader",
            "value": 0.7685731,
            "app_id": "main"
          },
          {
            "id": "ai_3DGtDKQp",
            "name": "couple",
            "value": 0.7593611,
            "app_id": "main"
          },
          {
            "id": "ai_Pf2b7clG",
            "name": "indoors",
            "value": 0.7316496,
            "app_id": "main"
          },
          {
            "id": "ai_TJ9wFfK5",
            "name": "portrait",
            "value": 0.7300092,
            "app_id": "main"
          },
          {
            "id": "ai_L3mzGfDT",
            "name": "offspring",
            "value": 0.72590846,
            "app_id": "main"
          }
        ]
      }
    }
  ]
}
